{
  "realm" : "user-realm",
  "users" : [ {
    "id" : "420476c7-7eb8-4422-adf9-2414f1f2b355",
    "username" : "rgs",
    "emailVerified" : true,
    "createdTimestamp" : 1740769031267,
    "enabled" : true,
    "totp" : false,
    "credentials" : [ {
      "id" : "e6707761-835b-400f-89e1-69cff40148be",
      "type" : "password",
      "createdDate" : 1740769031282,
      "secretData" : "{\"value\":\"LVFMzyqoPMQG3jCkZLtZfg47LQzmfzzmNATbmG7Z5Wk=\",\"salt\":\"ATahzvrr82oTSbDL4sOcnw==\",\"additionalParameters\":{}}",
      "credentialData" : "{\"hashIterations\":5,\"algorithm\":\"argon2\",\"additionalParameters\":{\"hashLength\":[\"32\"],\"memory\":[\"7168\"],\"type\":[\"id\"],\"version\":[\"1.3\"],\"parallelism\":[\"1\"]}}"
    } ],
    "disableableCredentialTypes" : [ ],
    "requiredActions" : [ ],
    "realmRoles" : [ "default-roles-user-realm" ],
    "clientRoles" : {
      "manav" : [ "customer" ]
    },
    "notBefore" : 0,
    "groups" : [ "/Dummy-Users" ]
  }, {
    "id" : "09597345-f670-4d29-bbc3-600a1da4ea2f",
    "username" : "r_h",
    "emailVerified" : true,
    "createdTimestamp" : 1740768407111,
    "enabled" : true,
    "totp" : false,
    "credentials" : [ {
      "id" : "54aa0449-ecf5-49b5-87cc-2334f5297805",
      "type" : "password",
      "createdDate" : 1740768407126,
      "secretData" : "{\"value\":\"gI1a66SBFF3BFz0gAIvd3SxVxi73GIjOHkYxnvmtJTw=\",\"salt\":\"5Qt+/DjMTjeWBaPJL72dTw==\",\"additionalParameters\":{}}",
      "credentialData" : "{\"hashIterations\":5,\"algorithm\":\"argon2\",\"additionalParameters\":{\"hashLength\":[\"32\"],\"memory\":[\"7168\"],\"type\":[\"id\"],\"version\":[\"1.3\"],\"parallelism\":[\"1\"]}}"
    } ],
    "disableableCredentialTypes" : [ ],
    "requiredActions" : [ ],
    "realmRoles" : [ "default-roles-user-realm" ],
    "clientRoles" : {
      "manav" : [ "customer" ]
    },
    "notBefore" : 0,
    "groups" : [ "/Dummy-Users" ]
  }, {
    "id" : "0c3bc162-1432-4771-8bc9-6690d4ebed10",
    "username" : "r_habib",
    "emailVerified" : true,
    "createdTimestamp" : 1740771236735,
    "enabled" : true,
    "totp" : false,
    "credentials" : [ {
      "id" : "413cfa4d-6ad2-4a3b-981e-af1f90c153fe",
      "type" : "password",
      "createdDate" : 1740771236750,
      "secretData" : "{\"value\":\"TeTdBx9ZAaXk73AYUKu0Su6wwkmEIyzBxwntl/LIzp4=\",\"salt\":\"FscfWciULSE9qR3+fe0jXQ==\",\"additionalParameters\":{}}",
      "credentialData" : "{\"hashIterations\":5,\"algorithm\":\"argon2\",\"additionalParameters\":{\"hashLength\":[\"32\"],\"memory\":[\"7168\"],\"type\":[\"id\"],\"version\":[\"1.3\"],\"parallelism\":[\"1\"]}}"
    } ],
    "disableableCredentialTypes" : [ ],
    "requiredActions" : [ ],
    "realmRoles" : [ "default-roles-user-realm" ],
    "clientRoles" : {
      "manav" : [ "customer" ]
    },
    "notBefore" : 0,
    "groups" : [ "/Dummy-Users" ]
  }, {
    "id" : "3731aa93-87a8-4bb4-a372-ce661adffd74",
    "username" : "rhavia",
    "emailVerified" : true,
    "createdTimestamp" : 1740772667707,
    "enabled" : true,
    "totp" : false,
    "credentials" : [ {
      "id" : "b752557f-aa09-4270-bad0-ba99416dc598",
      "type" : "password",
      "createdDate" : 1740772667727,
      "secretData" : "{\"value\":\"HsPq+qjEsQWNrhku3gHJ4xJCujh5oKYmq+KXOJhK5+Q=\",\"salt\":\"LJBR3b8LhzbPJ6AEpSPRjA==\",\"additionalParameters\":{}}",
      "credentialData" : "{\"hashIterations\":5,\"algorithm\":\"argon2\",\"additionalParameters\":{\"hashLength\":[\"32\"],\"memory\":[\"7168\"],\"type\":[\"id\"],\"version\":[\"1.3\"],\"parallelism\":[\"1\"]}}"
    } ],
    "disableableCredentialTypes" : [ ],
    "requiredActions" : [ ],
    "realmRoles" : [ "default-roles-user-realm" ],
    "clientRoles" : {
      "manav" : [ "customer" ]
    },
    "notBefore" : 0,
    "groups" : [ "/Dummy-Users" ]
  }, {
    "id" : "5360790a-af10-4da9-baa5-45971408174a",
    "username" : "rhea_mcgee",
    "emailVerified" : true,
    "createdTimestamp" : 1740772109318,
    "enabled" : true,
    "totp" : false,
    "credentials" : [ {
      "id" : "93185185-7268-4f76-bbd5-b442cf6171be",
      "type" : "password",
      "createdDate" : 1740772109334,
      "secretData" : "{\"value\":\"LPHBo1ZxU19SMFCmRoDCFLB6IQ5IkXS3az/Z+zkznac=\",\"salt\":\"izsvVzZgWYwv++U5S64Lng==\",\"additionalParameters\":{}}",
      "credentialData" : "{\"hashIterations\":5,\"algorithm\":\"argon2\",\"additionalParameters\":{\"hashLength\":[\"32\"],\"memory\":[\"7168\"],\"type\":[\"id\"],\"version\":[\"1.3\"],\"parallelism\":[\"1\"]}}"
    } ],
    "disableableCredentialTypes" : [ ],
    "requiredActions" : [ ],
    "realmRoles" : [ "default-roles-user-realm" ],
    "clientRoles" : {
      "manav" : [ "customer" ]
    },
    "notBefore" : 0,
    "groups" : [ "/Dummy-Users" ]
  }, {
    "id" : "72ee0aae-f799-4de0-8df7-a0c135721f54",
    "username" : "r_hernandez",
    "emailVerified" : true,
    "createdTimestamp" : 1740769642319,
    "enabled" : true,
    "totp" : false,
    "credentials" : [ {
      "id" : "bfdacb00-2db0-4e13-b7a5-31acbbab8d7b",
      "type" : "password",
      "createdDate" : 1740769642335,
      "secretData" : "{\"value\":\"WF99WVGm/EMwidb3ASG0xbhn6BfJhSC98ufefyl4i+A=\",\"salt\":\"RFNpOduPw3sDmKnJJK1zkg==\",\"additionalParameters\":{}}",
      "credentialData" : "{\"hashIterations\":5,\"algorithm\":\"argon2\",\"additionalParameters\":{\"hashLength\":[\"32\"],\"memory\":[\"7168\"],\"type\":[\"id\"],\"version\":[\"1.3\"],\"parallelism\":[\"1\"]}}"
    } ],
    "disableableCredentialTypes" : [ ],
    "requiredActions" : [ ],
    "realmRoles" : [ "default-roles-user-realm" ],
    "clientRoles" : {
      "manav" : [ "customer" ]
    },
    "notBefore" : 0,
    "groups" : [ "/Dummy-Users" ]
  }, {
    "id" : "4cbafdae-089e-47d4-82f1-b0726cb74f2d",
    "username" : "rhettsgirl1985",
    "emailVerified" : true,
    "createdTimestamp" : 1740768121926,
    "enabled" : true,
    "totp" : false,
    "credentials" : [ {
      "id" : "688f3c45-0b8e-4c77-b6b4-195ddc073ed9",
      "type" : "password",
      "createdDate" : 1740768121941,
      "secretData" : "{\"value\":\"EewmmDD3Zf1Z90ossooPaDeyqksrBvGsNyF695phXdg=\",\"salt\":\"U6oRVO/tSWzCzo9LGWrsbA==\",\"additionalParameters\":{}}",
      "credentialData" : "{\"hashIterations\":5,\"algorithm\":\"argon2\",\"additionalParameters\":{\"hashLength\":[\"32\"],\"memory\":[\"7168\"],\"type\":[\"id\"],\"version\":[\"1.3\"],\"parallelism\":[\"1\"]}}"
    } ],
    "disableableCredentialTypes" : [ ],
    "requiredActions" : [ ],
    "realmRoles" : [ "default-roles-user-realm" ],
    "clientRoles" : {
      "manav" : [ "customer" ]
    },
    "notBefore" : 0,
    "groups" : [ "/Dummy-Users" ]
  }, {
    "id" : "843c43c5-c6ce-4acb-97e6-12dfec4ad279",
    "username" : "rhiannon",
    "emailVerified" : true,
    "createdTimestamp" : 1740768688583,
    "enabled" : true,
    "totp" : false,
    "credentials" : [ {
      "id" : "995ddc94-52f9-4fe5-a598-7f6da1af3a21",
      "type" : "password",
      "createdDate" : 1740768688598,
      "secretData" : "{\"value\":\"CkCgOPG2Ck/FI5sdjwMhot3R1ZfpvVh/8uvRvK3klVo=\",\"salt\":\"cKce7repsC53vYI7Y5JU8w==\",\"additionalParameters\":{}}",
      "credentialData" : "{\"hashIterations\":5,\"algorithm\":\"argon2\",\"additionalParameters\":{\"hashLength\":[\"32\"],\"memory\":[\"7168\"],\"type\":[\"id\"],\"version\":[\"1.3\"],\"parallelism\":[\"1\"]}}"
    } ],
    "disableableCredentialTypes" : [ ],
    "requiredActions" : [ ],
    "realmRoles" : [ "default-roles-user-realm" ],
    "clientRoles" : {
      "manav" : [ "customer" ]
    },
    "notBefore" : 0,
    "groups" : [ "/Dummy-Users" ]
  }, {
    "id" : "1198a266-affb-4a4d-b1ba-fdb849f6bdd5",
    "username" : "rhino8229",
    "emailVerified" : true,
    "createdTimestamp" : 1740771304497,
    "enabled" : true,
    "totp" : false,
    "credentials" : [ {
      "id" : "9815c623-3531-49c9-b5a6-8272e580cc4b",
      "type" : "password",
      "createdDate" : 1740771304516,
      "secretData" : "{\"value\":\"V87P0td0BgGT9/fgidq3NFM1/DO0Xqk1kI0IpDHdHkk=\",\"salt\":\"KZFobGTVW3Y6ePezyVUXYQ==\",\"additionalParameters\":{}}",
      "credentialData" : "{\"hashIterations\":5,\"algorithm\":\"argon2\",\"additionalParameters\":{\"hashLength\":[\"32\"],\"memory\":[\"7168\"],\"type\":[\"id\"],\"version\":[\"1.3\"],\"parallelism\":[\"1\"]}}"
    } ],
    "disableableCredentialTypes" : [ ],
    "requiredActions" : [ ],
    "realmRoles" : [ "default-roles-user-realm" ],
    "clientRoles" : {
      "manav" : [ "customer" ]
    },
    "notBefore" : 0,
    "groups" : [ "/Dummy-Users" ]
  }, {
    "id" : "301e7552-954e-4342-ad25-d1fdeff70a62",
    "username" : "r.h._mccort",
    "emailVerified" : true,
    "createdTimestamp" : 1740771202486,
    "enabled" : true,
    "totp" : false,
    "credentials" : [ {
      "id" : "544e7a76-758a-442a-ad78-e97f6732a9c7",
      "type" : "password",
      "createdDate" : 1740771202501,
      "secretData" : "{\"value\":\"+pspTLdeX263SI7yD4DvUScpqazbfWxoHQvfYeyQok8=\",\"salt\":\"pTHyZqN5yZn4iC/3yc5lfg==\",\"additionalParameters\":{}}",
      "credentialData" : "{\"hashIterations\":5,\"algorithm\":\"argon2\",\"additionalParameters\":{\"hashLength\":[\"32\"],\"memory\":[\"7168\"],\"type\":[\"id\"],\"version\":[\"1.3\"],\"parallelism\":[\"1\"]}}"
    } ],
    "disableableCredentialTypes" : [ ],
    "requiredActions" : [ ],
    "realmRoles" : [ "default-roles-user-realm" ],
    "clientRoles" : {
      "manav" : [ "customer" ]
    },
    "notBefore" : 0,
    "groups" : [ "/Dummy-Users" ]
  }, {
    "id" : "1609d30e-aecf-4e20-aa83-7e30e87f3263",
    "username" : "rhoda",
    "emailVerified" : true,
    "createdTimestamp" : 1740771502145,
    "enabled" : true,
    "totp" : false,
    "credentials" : [ {
      "id" : "b8dbd6ad-d1c5-4cdb-ba91-e3b3173d98dd",
      "type" : "password",
      "createdDate" : 1740771502163,
      "secretData" : "{\"value\":\"Ezr4RaN5wvAkDNC3MgcdBxoBoygzoj01RvsbndZVMf4=\",\"salt\":\"qnFZGE77+AU/9bSoR/u6Yw==\",\"additionalParameters\":{}}",
      "credentialData" : "{\"hashIterations\":5,\"algorithm\":\"argon2\",\"additionalParameters\":{\"hashLength\":[\"32\"],\"memory\":[\"7168\"],\"type\":[\"id\"],\"version\":[\"1.3\"],\"parallelism\":[\"1\"]}}"
    } ],
    "disableableCredentialTypes" : [ ],
    "requiredActions" : [ ],
    "realmRoles" : [ "default-roles-user-realm" ],
    "clientRoles" : {
      "manav" : [ "customer" ]
    },
    "notBefore" : 0,
    "groups" : [ "/Dummy-Users" ]
  }, {
    "id" : "cfadb41f-e5f3-4da5-96f2-9a261cbdf331",
    "username" : "rhonda",
    "emailVerified" : true,
    "createdTimestamp" : 1740767602111,
    "enabled" : true,
    "totp" : false,
    "credentials" : [ {
      "id" : "59b88870-5ddb-44ce-a31e-cba37aec4ef0",
      "type" : "password",
      "createdDate" : 1740767602126,
      "secretData" : "{\"value\":\"1XpnG0G301X3dIkWpPjo2xVbeuNo9zclojHghvWUn9Q=\",\"salt\":\"ALO1rbkyun+o6XS8q0/U1A==\",\"additionalParameters\":{}}",
      "credentialData" : "{\"hashIterations\":5,\"algorithm\":\"argon2\",\"additionalParameters\":{\"hashLength\":[\"32\"],\"memory\":[\"7168\"],\"type\":[\"id\"],\"version\":[\"1.3\"],\"parallelism\":[\"1\"]}}"
    } ],
    "disableableCredentialTypes" : [ ],
    "requiredActions" : [ ],
    "realmRoles" : [ "default-roles-user-realm" ],
    "clientRoles" : {
      "manav" : [ "customer" ]
    },
    "notBefore" : 0,
    "groups" : [ "/Dummy-Users" ]
  }, {
    "id" : "83480f5b-5eed-4445-b961-8f3eccda82c9",
    "username" : "rhonda_brown",
    "emailVerified" : true,
    "createdTimestamp" : 1740767400683,
    "enabled" : true,
    "totp" : false,
    "credentials" : [ {
      "id" : "1cd599a6-dd67-4c11-9f16-8c2e4f872f07",
      "type" : "password",
      "createdDate" : 1740767400699,
      "secretData" : "{\"value\":\"p7/Ej7b9pYlkS2qy/vFCViCfpjMITNa6FHActZp3ZZg=\",\"salt\":\"kM6QrfL1JUye7nkjkKINCQ==\",\"additionalParameters\":{}}",
      "credentialData" : "{\"hashIterations\":5,\"algorithm\":\"argon2\",\"additionalParameters\":{\"hashLength\":[\"32\"],\"memory\":[\"7168\"],\"type\":[\"id\"],\"version\":[\"1.3\"],\"parallelism\":[\"1\"]}}"
    } ],
    "disableableCredentialTypes" : [ ],
    "requiredActions" : [ ],
    "realmRoles" : [ "default-roles-user-realm" ],
    "clientRoles" : {
      "manav" : [ "customer" ]
    },
    "notBefore" : 0,
    "groups" : [ "/Dummy-Users" ]
  }, {
    "id" : "c6e05f1f-60ab-45ce-8faa-191ea7b5d944",
    "username" : "rhonda_gladden",
    "emailVerified" : true,
    "createdTimestamp" : 1740771149866,
    "enabled" : true,
    "totp" : false,
    "credentials" : [ {
      "id" : "2fa4107b-ac3e-4a84-ad5e-557ce556b852",
      "type" : "password",
      "createdDate" : 1740771149882,
      "secretData" : "{\"value\":\"+lX9dZitdrNtDX5x7KMNxKjjgz30NoEbEpWtGx2+H8A=\",\"salt\":\"AYDJ1wLxGGsbhM4NG6ia/w==\",\"additionalParameters\":{}}",
      "credentialData" : "{\"hashIterations\":5,\"algorithm\":\"argon2\",\"additionalParameters\":{\"hashLength\":[\"32\"],\"memory\":[\"7168\"],\"type\":[\"id\"],\"version\":[\"1.3\"],\"parallelism\":[\"1\"]}}"
    } ],
    "disableableCredentialTypes" : [ ],
    "requiredActions" : [ ],
    "realmRoles" : [ "default-roles-user-realm" ],
    "clientRoles" : {
      "manav" : [ "customer" ]
    },
    "notBefore" : 0,
    "groups" : [ "/Dummy-Users" ]
  }, {
    "id" : "516299fc-09e0-464a-85c2-fff2bd033272",
    "username" : "rhonda_hillstrom",
    "emailVerified" : true,
    "createdTimestamp" : 1740768552930,
    "enabled" : true,
    "totp" : false,
    "credentials" : [ {
      "id" : "8ccc0144-7944-486d-8c26-aa6915a0ccd2",
      "type" : "password",
      "createdDate" : 1740768552946,
      "secretData" : "{\"value\":\"1lzj5CPG+N8z5fnxRXrznYpd3nGoCza+DeAKgG0BQjk=\",\"salt\":\"aH1MOCOLV8UWY79ssj/wTw==\",\"additionalParameters\":{}}",
      "credentialData" : "{\"hashIterations\":5,\"algorithm\":\"argon2\",\"additionalParameters\":{\"hashLength\":[\"32\"],\"memory\":[\"7168\"],\"type\":[\"id\"],\"version\":[\"1.3\"],\"parallelism\":[\"1\"]}}"
    } ],
    "disableableCredentialTypes" : [ ],
    "requiredActions" : [ ],
    "realmRoles" : [ "default-roles-user-realm" ],
    "clientRoles" : {
      "manav" : [ "customer" ]
    },
    "notBefore" : 0,
    "groups" : [ "/Dummy-Users" ]
  }, {
    "id" : "b44205cf-cd2c-488d-95b3-210dc85cf6e5",
    "username" : "rhonda_j",
    "emailVerified" : true,
    "createdTimestamp" : 1740769528354,
    "enabled" : true,
    "totp" : false,
    "credentials" : [ {
      "id" : "b5a821c6-f50a-4498-a652-b75b6bc6ec84",
      "type" : "password",
      "createdDate" : 1740769528368,
      "secretData" : "{\"value\":\"5CUv7bvZ3KiiRv0L4tza9WEsncjVFHe/lWVJ3KCOrAs=\",\"salt\":\"9dXuts6izw1xpBTeUHpWSQ==\",\"additionalParameters\":{}}",
      "credentialData" : "{\"hashIterations\":5,\"algorithm\":\"argon2\",\"additionalParameters\":{\"hashLength\":[\"32\"],\"memory\":[\"7168\"],\"type\":[\"id\"],\"version\":[\"1.3\"],\"parallelism\":[\"1\"]}}"
    } ],
    "disableableCredentialTypes" : [ ],
    "requiredActions" : [ ],
    "realmRoles" : [ "default-roles-user-realm" ],
    "clientRoles" : {
      "manav" : [ "customer" ]
    },
    "notBefore" : 0,
    "groups" : [ "/Dummy-Users" ]
  }, {
    "id" : "144c344d-92d8-4707-921b-86bb080f620d",
    "username" : "rhonda_mccoy",
    "emailVerified" : true,
    "createdTimestamp" : 1740767336162,
    "enabled" : true,
    "totp" : false,
    "credentials" : [ {
      "id" : "09936ad9-73e3-4169-a7e4-2752611b6e99",
      "type" : "password",
      "createdDate" : 1740767336176,
      "secretData" : "{\"value\":\"K40MvavDR4Zv8fbPVlZyHPaCy/T1GB0zwS+6ztGYVGA=\",\"salt\":\"cnNF03zxr8CwZJICLqMyIQ==\",\"additionalParameters\":{}}",
      "credentialData" : "{\"hashIterations\":5,\"algorithm\":\"argon2\",\"additionalParameters\":{\"hashLength\":[\"32\"],\"memory\":[\"7168\"],\"type\":[\"id\"],\"version\":[\"1.3\"],\"parallelism\":[\"1\"]}}"
    } ],
    "disableableCredentialTypes" : [ ],
    "requiredActions" : [ ],
    "realmRoles" : [ "default-roles-user-realm" ],
    "clientRoles" : {
      "manav" : [ "customer" ]
    },
    "notBefore" : 0,
    "groups" : [ "/Dummy-Users" ]
  }, {
    "id" : "b8ab1a2e-3592-493e-881c-d4e772c52e09",
    "username" : "rhonda_moore",
    "emailVerified" : true,
    "createdTimestamp" : 1740769406665,
    "enabled" : true,
    "totp" : false,
    "credentials" : [ {
      "id" : "3c8ee957-2752-4bf6-b1d1-f1bb2e5b3b37",
      "type" : "password",
      "createdDate" : 1740769406680,
      "secretData" : "{\"value\":\"EvNJ+yVYQOssvYG9hyTsDszgWXtuBvni0lzR7KArKwk=\",\"salt\":\"Ej+2nBWQqd2SwkvAODjfgg==\",\"additionalParameters\":{}}",
      "credentialData" : "{\"hashIterations\":5,\"algorithm\":\"argon2\",\"additionalParameters\":{\"hashLength\":[\"32\"],\"memory\":[\"7168\"],\"type\":[\"id\"],\"version\":[\"1.3\"],\"parallelism\":[\"1\"]}}"
    } ],
    "disableableCredentialTypes" : [ ],
    "requiredActions" : [ ],
    "realmRoles" : [ "default-roles-user-realm" ],
    "clientRoles" : {
      "manav" : [ "customer" ]
    },
    "notBefore" : 0,
    "groups" : [ "/Dummy-Users" ]
  }, {
    "id" : "6070d1b0-3755-43ea-af01-8cc1306de51b",
    "username" : "rhonda_tinker",
    "emailVerified" : true,
    "createdTimestamp" : 1740768829732,
    "enabled" : true,
    "totp" : false,
    "credentials" : [ {
      "id" : "ec640d18-8340-4e61-9632-ad328f6eaca9",
      "type" : "password",
      "createdDate" : 1740768829747,
      "secretData" : "{\"value\":\"Js91u7IDoktI/Z2KhXpkCsBRpDFeEUGOVouPmCVSND0=\",\"salt\":\"5IWJsaOmR0zue3qcc9bh4g==\",\"additionalParameters\":{}}",
      "credentialData" : "{\"hashIterations\":5,\"algorithm\":\"argon2\",\"additionalParameters\":{\"hashLength\":[\"32\"],\"memory\":[\"7168\"],\"type\":[\"id\"],\"version\":[\"1.3\"],\"parallelism\":[\"1\"]}}"
    } ],
    "disableableCredentialTypes" : [ ],
    "requiredActions" : [ ],
    "realmRoles" : [ "default-roles-user-realm" ],
    "clientRoles" : {
      "manav" : [ "customer" ]
    },
    "notBefore" : 0,
    "groups" : [ "/Dummy-Users" ]
  }, {
    "id" : "703b66d2-d4ff-4187-bc4d-0fcc7a365bdf",
    "username" : "rhonda_wood",
    "emailVerified" : true,
    "createdTimestamp" : 1740770063004,
    "enabled" : true,
    "totp" : false,
    "credentials" : [ {
      "id" : "f46f52ab-57be-4c59-8e0e-5b05ac57d4d2",
      "type" : "password",
      "createdDate" : 1740770063018,
      "secretData" : "{\"value\":\"UgrjxADOJYHWpDkRiZiGXrUuVY5cY2b3DU+vPQRAiWk=\",\"salt\":\"HZtR2fzfVZGmxJy8PUieaA==\",\"additionalParameters\":{}}",
      "credentialData" : "{\"hashIterations\":5,\"algorithm\":\"argon2\",\"additionalParameters\":{\"hashLength\":[\"32\"],\"memory\":[\"7168\"],\"type\":[\"id\"],\"version\":[\"1.3\"],\"parallelism\":[\"1\"]}}"
    } ],
    "disableableCredentialTypes" : [ ],
    "requiredActions" : [ ],
    "realmRoles" : [ "default-roles-user-realm" ],
    "clientRoles" : {
      "manav" : [ "customer" ]
    },
    "notBefore" : 0,
    "groups" : [ "/Dummy-Users" ]
  }, {
    "id" : "366ed288-dc85-433f-b5f5-b901553b30f9",
    "username" : "r._horr._hor",
    "emailVerified" : true,
    "createdTimestamp" : 1740770155584,
    "enabled" : true,
    "totp" : false,
    "credentials" : [ {
      "id" : "348cea3c-1750-437f-ac80-713832bf27c2",
      "type" : "password",
      "createdDate" : 1740770155601,
      "secretData" : "{\"value\":\"7EC1rAyOL8j1upfcYBTlY+RTMXJPEHjZLn4mD+fiA4I=\",\"salt\":\"i+83jJuRxsYASMIyireKZQ==\",\"additionalParameters\":{}}",
      "credentialData" : "{\"hashIterations\":5,\"algorithm\":\"argon2\",\"additionalParameters\":{\"hashLength\":[\"32\"],\"memory\":[\"7168\"],\"type\":[\"id\"],\"version\":[\"1.3\"],\"parallelism\":[\"1\"]}}"
    } ],
    "disableableCredentialTypes" : [ ],
    "requiredActions" : [ ],
    "realmRoles" : [ "default-roles-user-realm" ],
    "clientRoles" : {
      "manav" : [ "customer" ]
    },
    "notBefore" : 0,
    "groups" : [ "/Dummy-Users" ]
  }, {
    "id" : "8912105f-d259-4394-9391-7156d4646f7b",
    "username" : "rhtfgrhtfg",
    "emailVerified" : true,
    "createdTimestamp" : 1740768989957,
    "enabled" : true,
    "totp" : false,
    "credentials" : [ {
      "id" : "d5226f7b-432c-4e28-8826-887555396b2c",
      "type" : "password",
      "createdDate" : 1740768989971,
      "secretData" : "{\"value\":\"pFFZsuST9ZbHXjzW7/0VQO9eU/tYMhJS+3GMoMHVB1w=\",\"salt\":\"Cml4oYrmMLBwlqdFUutftA==\",\"additionalParameters\":{}}",
      "credentialData" : "{\"hashIterations\":5,\"algorithm\":\"argon2\",\"additionalParameters\":{\"hashLength\":[\"32\"],\"memory\":[\"7168\"],\"type\":[\"id\"],\"version\":[\"1.3\"],\"parallelism\":[\"1\"]}}"
    } ],
    "disableableCredentialTypes" : [ ],
    "requiredActions" : [ ],
    "realmRoles" : [ "default-roles-user-realm" ],
    "clientRoles" : {
      "manav" : [ "customer" ]
    },
    "notBefore" : 0,
    "groups" : [ "/Dummy-Users" ]
  }, {
    "id" : "aa21b4c7-78d4-4f4e-917c-8647b9cdddfd",
    "username" : "rhyan_craig",
    "emailVerified" : true,
    "createdTimestamp" : 1740767397687,
    "enabled" : true,
    "totp" : false,
    "credentials" : [ {
      "id" : "1f8ae024-efb8-4e49-9568-6d45cab72b5a",
      "type" : "password",
      "createdDate" : 1740767397703,
      "secretData" : "{\"value\":\"Ohwdn+9amVrKe4M/oQOimjsPWnCCpbRqq/f73j28DKU=\",\"salt\":\"BhA3GIpIKChmJP5E86GBnA==\",\"additionalParameters\":{}}",
      "credentialData" : "{\"hashIterations\":5,\"algorithm\":\"argon2\",\"additionalParameters\":{\"hashLength\":[\"32\"],\"memory\":[\"7168\"],\"type\":[\"id\"],\"version\":[\"1.3\"],\"parallelism\":[\"1\"]}}"
    } ],
    "disableableCredentialTypes" : [ ],
    "requiredActions" : [ ],
    "realmRoles" : [ "default-roles-user-realm" ],
    "clientRoles" : {
      "manav" : [ "customer" ]
    },
    "notBefore" : 0,
    "groups" : [ "/Dummy-Users" ]
  }, {
    "id" : "2da702c4-8624-4f9d-bc0e-2c568c70d839",
    "username" : "riaan_van_der_watt",
    "emailVerified" : true,
    "createdTimestamp" : 1740767789805,
    "enabled" : true,
    "totp" : false,
    "credentials" : [ {
      "id" : "e6ca798c-67fd-4a51-88f5-a4a8b03fbc0a",
      "type" : "password",
      "createdDate" : 1740767789822,
      "secretData" : "{\"value\":\"rJ2JHEnHovLKXuEblAMeiUhRwBN4Dp4JpJpJy+/SXkw=\",\"salt\":\"VgUtZIUL5HEgJZlNmwV/aw==\",\"additionalParameters\":{}}",
      "credentialData" : "{\"hashIterations\":5,\"algorithm\":\"argon2\",\"additionalParameters\":{\"hashLength\":[\"32\"],\"memory\":[\"7168\"],\"type\":[\"id\"],\"version\":[\"1.3\"],\"parallelism\":[\"1\"]}}"
    } ],
    "disableableCredentialTypes" : [ ],
    "requiredActions" : [ ],
    "realmRoles" : [ "default-roles-user-realm" ],
    "clientRoles" : {
      "manav" : [ "customer" ]
    },
    "notBefore" : 0,
    "groups" : [ "/Dummy-Users" ]
  }, {
    "id" : "5cc71558-b88e-4080-8806-d2317175069a",
    "username" : "ricardo",
    "emailVerified" : true,
    "createdTimestamp" : 1740769563041,
    "enabled" : true,
    "totp" : false,
    "credentials" : [ {
      "id" : "03bcd87e-0af1-4c3c-9a2f-65d9bef5c6f6",
      "type" : "password",
      "createdDate" : 1740769563055,
      "secretData" : "{\"value\":\"eKqdDKGwosM1ZjFQsXWaNhflXTaAoklx+//1qcngoS0=\",\"salt\":\"i3P7nfXPkHDSsjMKl2E0HQ==\",\"additionalParameters\":{}}",
      "credentialData" : "{\"hashIterations\":5,\"algorithm\":\"argon2\",\"additionalParameters\":{\"hashLength\":[\"32\"],\"memory\":[\"7168\"],\"type\":[\"id\"],\"version\":[\"1.3\"],\"parallelism\":[\"1\"]}}"
    } ],
    "disableableCredentialTypes" : [ ],
    "requiredActions" : [ ],
    "realmRoles" : [ "default-roles-user-realm" ],
    "clientRoles" : {
      "manav" : [ "customer" ]
    },
    "notBefore" : 0,
    "groups" : [ "/Dummy-Users" ]
  }, {
    "id" : "82c2a4ad-e761-4827-9794-7d930c1005d6",
    "username" : "ricardo_castro",
    "emailVerified" : true,
    "createdTimestamp" : 1740768287140,
    "enabled" : true,
    "totp" : false,
    "credentials" : [ {
      "id" : "39c9f4c1-8f90-404e-a8f8-9a4977f7931d",
      "type" : "password",
      "createdDate" : 1740768287157,
      "secretData" : "{\"value\":\"8o+inWOkJn71vJMxYu3q1b+aMP9H9JO6YoSWibjJBtg=\",\"salt\":\"TAtQ4vrGdL5mWGOghpy4sg==\",\"additionalParameters\":{}}",
      "credentialData" : "{\"hashIterations\":5,\"algorithm\":\"argon2\",\"additionalParameters\":{\"hashLength\":[\"32\"],\"memory\":[\"7168\"],\"type\":[\"id\"],\"version\":[\"1.3\"],\"parallelism\":[\"1\"]}}"
    } ],
    "disableableCredentialTypes" : [ ],
    "requiredActions" : [ ],
    "realmRoles" : [ "default-roles-user-realm" ],
    "clientRoles" : {
      "manav" : [ "customer" ]
    },
    "notBefore" : 0,
    "groups" : [ "/Dummy-Users" ]
  }, {
    "id" : "59719561-ee63-4402-9b4b-16b67eaddd3b",
    "username" : "ricardo_m",
    "emailVerified" : true,
    "createdTimestamp" : 1740770057447,
    "enabled" : true,
    "totp" : false,
    "credentials" : [ {
      "id" : "ee1aae01-53d1-423a-bd7a-74701a4153e0",
      "type" : "password",
      "createdDate" : 1740770057462,
      "secretData" : "{\"value\":\"Ouw7qYbdZ+EiTZMbBA0Ii/hpUj/h8jQG8c5JWZr2UN0=\",\"salt\":\"nAs0LnogmzX0mNxJ0cLyCg==\",\"additionalParameters\":{}}",
      "credentialData" : "{\"hashIterations\":5,\"algorithm\":\"argon2\",\"additionalParameters\":{\"hashLength\":[\"32\"],\"memory\":[\"7168\"],\"type\":[\"id\"],\"version\":[\"1.3\"],\"parallelism\":[\"1\"]}}"
    } ],
    "disableableCredentialTypes" : [ ],
    "requiredActions" : [ ],
    "realmRoles" : [ "default-roles-user-realm" ],
    "clientRoles" : {
      "manav" : [ "customer" ]
    },
    "notBefore" : 0,
    "groups" : [ "/Dummy-Users" ]
  }, {
    "id" : "61dc2033-b692-4791-83c5-c762af6271a9",
    "username" : "ricardo_montoya",
    "emailVerified" : true,
    "createdTimestamp" : 1740768978502,
    "enabled" : true,
    "totp" : false,
    "credentials" : [ {
      "id" : "d897fe84-1eb1-4f8f-ae90-0c557e536507",
      "type" : "password",
      "createdDate" : 1740768978516,
      "secretData" : "{\"value\":\"iSkgXyCjZWxqxlrnSzlKgHNOSYPvbfV59OPTSlC88/Q=\",\"salt\":\"FTKyOA+lJNC6P90dC1FeKw==\",\"additionalParameters\":{}}",
      "credentialData" : "{\"hashIterations\":5,\"algorithm\":\"argon2\",\"additionalParameters\":{\"hashLength\":[\"32\"],\"memory\":[\"7168\"],\"type\":[\"id\"],\"version\":[\"1.3\"],\"parallelism\":[\"1\"]}}"
    } ],
    "disableableCredentialTypes" : [ ],
    "requiredActions" : [ ],
    "realmRoles" : [ "default-roles-user-realm" ],
    "clientRoles" : {
      "manav" : [ "customer" ]
    },
    "notBefore" : 0,
    "groups" : [ "/Dummy-Users" ]
  }, {
    "id" : "7cb74059-ab54-4e41-995c-47e0340fc01b",
    "username" : "ricardo_napoles",
    "emailVerified" : true,
    "createdTimestamp" : 1740770122625,
    "enabled" : true,
    "totp" : false,
    "credentials" : [ {
      "id" : "e7ff1dc5-bfb8-47c5-a31d-ab402a5529bb",
      "type" : "password",
      "createdDate" : 1740770122640,
      "secretData" : "{\"value\":\"tcP2/3bYE2qddMBj8DaAzJv6mgsY18NLhxGAc8FtgcU=\",\"salt\":\"bsGO79D2MY/et4MxRt8Rrw==\",\"additionalParameters\":{}}",
      "credentialData" : "{\"hashIterations\":5,\"algorithm\":\"argon2\",\"additionalParameters\":{\"hashLength\":[\"32\"],\"memory\":[\"7168\"],\"type\":[\"id\"],\"version\":[\"1.3\"],\"parallelism\":[\"1\"]}}"
    } ],
    "disableableCredentialTypes" : [ ],
    "requiredActions" : [ ],
    "realmRoles" : [ "default-roles-user-realm" ],
    "clientRoles" : {
      "manav" : [ "customer" ]
    },
    "notBefore" : 0,
    "groups" : [ "/Dummy-Users" ]
  }, {
    "id" : "9d6c17d9-937c-49d8-893a-6b9c569aabeb",
    "username" : "ricardo_schemelensky",
    "emailVerified" : true,
    "createdTimestamp" : 1740770056914,
    "enabled" : true,
    "totp" : false,
    "credentials" : [ {
      "id" : "613ed623-367a-4b5f-9694-c2589a0047b0",
      "type" : "password",
      "createdDate" : 1740770056929,
      "secretData" : "{\"value\":\"4zlsY82bxVI9sYb5s/LM3lKMuI+uoYtmouNmRQfEQ6I=\",\"salt\":\"PIs0XkmShLv+/dX+ZOyFyA==\",\"additionalParameters\":{}}",
      "credentialData" : "{\"hashIterations\":5,\"algorithm\":\"argon2\",\"additionalParameters\":{\"hashLength\":[\"32\"],\"memory\":[\"7168\"],\"type\":[\"id\"],\"version\":[\"1.3\"],\"parallelism\":[\"1\"]}}"
    } ],
    "disableableCredentialTypes" : [ ],
    "requiredActions" : [ ],
    "realmRoles" : [ "default-roles-user-realm" ],
    "clientRoles" : {
      "manav" : [ "customer" ]
    },
    "notBefore" : 0,
    "groups" : [ "/Dummy-Users" ]
  }, {
    "id" : "b2dcdb8f-577b-4a08-8533-58a91f1d847f",
    "username" : "rich",
    "emailVerified" : true,
    "createdTimestamp" : 1740769070352,
    "enabled" : true,
    "totp" : false,
    "credentials" : [ {
      "id" : "6a298e69-fef2-4e75-97b8-814a612111f5",
      "type" : "password",
      "createdDate" : 1740769070367,
      "secretData" : "{\"value\":\"M//e8kMbp6/T1YMDza53ZptSv/ADMkqsMIGpnpRZKso=\",\"salt\":\"BQA1Il0nxLK/kgBoqMa81g==\",\"additionalParameters\":{}}",
      "credentialData" : "{\"hashIterations\":5,\"algorithm\":\"argon2\",\"additionalParameters\":{\"hashLength\":[\"32\"],\"memory\":[\"7168\"],\"type\":[\"id\"],\"version\":[\"1.3\"],\"parallelism\":[\"1\"]}}"
    } ],
    "disableableCredentialTypes" : [ ],
    "requiredActions" : [ ],
    "realmRoles" : [ "default-roles-user-realm" ],
    "clientRoles" : {
      "manav" : [ "customer" ]
    },
    "notBefore" : 0,
    "groups" : [ "/Dummy-Users" ]
  }, {
    "id" : "b1778d0f-9176-4285-b78f-e2077399ef00",
    "username" : "richard",
    "emailVerified" : true,
    "createdTimestamp" : 1740768469042,
    "enabled" : true,
    "totp" : false,
    "credentials" : [ {
      "id" : "395ddc81-2bdc-4cc5-988b-b2907f486508",
      "type" : "password",
      "createdDate" : 1740768469057,
      "secretData" : "{\"value\":\"o2tE7fcdBX3Y/4WpHbjmfTwmIvklnO6uX2YUG2xOUXo=\",\"salt\":\"Bkf7ZHHBvdgNDjj0r9eQ0Q==\",\"additionalParameters\":{}}",
      "credentialData" : "{\"hashIterations\":5,\"algorithm\":\"argon2\",\"additionalParameters\":{\"hashLength\":[\"32\"],\"memory\":[\"7168\"],\"type\":[\"id\"],\"version\":[\"1.3\"],\"parallelism\":[\"1\"]}}"
    } ],
    "disableableCredentialTypes" : [ ],
    "requiredActions" : [ ],
    "realmRoles" : [ "default-roles-user-realm" ],
    "clientRoles" : {
      "manav" : [ "customer" ]
    },
    "notBefore" : 0,
    "groups" : [ "/Dummy-Users" ]
  }, {
    "id" : "07f4edaa-e841-4953-a1b0-6ea7ef70f75b",
    "username" : "richard_a.",
    "emailVerified" : true,
    "createdTimestamp" : 1740769080776,
    "enabled" : true,
    "totp" : false,
    "credentials" : [ {
      "id" : "4652b3b0-a66b-4b1b-aa40-2665cbcb79b1",
      "type" : "password",
      "createdDate" : 1740769080791,
      "secretData" : "{\"value\":\"NnqGGzPxJ1qIiXWn92QuDrurqXGCW2NJLSYdSxpI/fc=\",\"salt\":\"pdsqoEfLKS0XpZfeOcRNgg==\",\"additionalParameters\":{}}",
      "credentialData" : "{\"hashIterations\":5,\"algorithm\":\"argon2\",\"additionalParameters\":{\"hashLength\":[\"32\"],\"memory\":[\"7168\"],\"type\":[\"id\"],\"version\":[\"1.3\"],\"parallelism\":[\"1\"]}}"
    } ],
    "disableableCredentialTypes" : [ ],
    "requiredActions" : [ ],
    "realmRoles" : [ "default-roles-user-realm" ],
    "clientRoles" : {
      "manav" : [ "customer" ]
    },
    "notBefore" : 0,
    "groups" : [ "/Dummy-Users" ]
  }, {
    "id" : "40f6afdd-d045-42da-9c22-7cae9433a374",
    "username" : "richard_baldwin",
    "emailVerified" : true,
    "createdTimestamp" : 1740769560940,
    "enabled" : true,
    "totp" : false,
    "credentials" : [ {
      "id" : "d6b188a1-0780-4c34-8de7-51742e297794",
      "type" : "password",
      "createdDate" : 1740769560954,
      "secretData" : "{\"value\":\"M6LCKqcGFzPRAYA7BoqZ787kKl4IbuL8uZjrwb3Oht4=\",\"salt\":\"PCF6tOcTROlu+tUEVDOecw==\",\"additionalParameters\":{}}",
      "credentialData" : "{\"hashIterations\":5,\"algorithm\":\"argon2\",\"additionalParameters\":{\"hashLength\":[\"32\"],\"memory\":[\"7168\"],\"type\":[\"id\"],\"version\":[\"1.3\"],\"parallelism\":[\"1\"]}}"
    } ],
    "disableableCredentialTypes" : [ ],
    "requiredActions" : [ ],
    "realmRoles" : [ "default-roles-user-realm" ],
    "clientRoles" : {
      "manav" : [ "customer" ]
    },
    "notBefore" : 0,
    "groups" : [ "/Dummy-Users" ]
  }, {
    "id" : "36be7966-8e9f-4053-b2ee-9d069a9a45dc",
    "username" : "richard_ballin",
    "emailVerified" : true,
    "createdTimestamp" : 1740772760310,
    "enabled" : true,
    "totp" : false,
    "credentials" : [ {
      "id" : "efb77cbd-fa50-4087-bb15-20f51ee08e4c",
      "type" : "password",
      "createdDate" : 1740772760326,
      "secretData" : "{\"value\":\"xbKzpPA5bOmLVxER4IKv4onzKZd1fnQvEU1TD2tA1Ys=\",\"salt\":\"DGPGtKU+TWFR8uy8BV4ZRg==\",\"additionalParameters\":{}}",
      "credentialData" : "{\"hashIterations\":5,\"algorithm\":\"argon2\",\"additionalParameters\":{\"hashLength\":[\"32\"],\"memory\":[\"7168\"],\"type\":[\"id\"],\"version\":[\"1.3\"],\"parallelism\":[\"1\"]}}"
    } ],
    "disableableCredentialTypes" : [ ],
    "requiredActions" : [ ],
    "realmRoles" : [ "default-roles-user-realm" ],
    "clientRoles" : {
      "manav" : [ "customer" ]
    },
    "notBefore" : 0,
    "groups" : [ "/Dummy-Users" ]
  }, {
    "id" : "249a4a1d-df71-4e62-962b-df6a9b168088",
    "username" : "richard_berry",
    "emailVerified" : true,
    "createdTimestamp" : 1740767590116,
    "enabled" : true,
    "totp" : false,
    "credentials" : [ {
      "id" : "76df3256-b815-4a94-8a67-8202692d9c87",
      "type" : "password",
      "createdDate" : 1740767590131,
      "secretData" : "{\"value\":\"HPcNUKAXGdgsQLyRjC1tcs0bDHkmlFCRLw3Kxofva+M=\",\"salt\":\"E8M0A7zItKvZ1F9VbgbnAQ==\",\"additionalParameters\":{}}",
      "credentialData" : "{\"hashIterations\":5,\"algorithm\":\"argon2\",\"additionalParameters\":{\"hashLength\":[\"32\"],\"memory\":[\"7168\"],\"type\":[\"id\"],\"version\":[\"1.3\"],\"parallelism\":[\"1\"]}}"
    } ],
    "disableableCredentialTypes" : [ ],
    "requiredActions" : [ ],
    "realmRoles" : [ "default-roles-user-realm" ],
    "clientRoles" : {
      "manav" : [ "customer" ]
    },
    "notBefore" : 0,
    "groups" : [ "/Dummy-Users" ]
  }, {
    "id" : "574693ff-5412-41dc-b980-cd0f4661a711",
    "username" : "richard_birch",
    "emailVerified" : true,
    "createdTimestamp" : 1740768653498,
    "enabled" : true,
    "totp" : false,
    "credentials" : [ {
      "id" : "220bdcc6-bc69-4140-891f-6cc5d92a2a14",
      "type" : "password",
      "createdDate" : 1740768653512,
      "secretData" : "{\"value\":\"GW34BfgusHbkp+w8fFQiqGLgMizgjQBK1W42jqbY+VM=\",\"salt\":\"pqCbVC+JVrX0dwhOjieavw==\",\"additionalParameters\":{}}",
      "credentialData" : "{\"hashIterations\":5,\"algorithm\":\"argon2\",\"additionalParameters\":{\"hashLength\":[\"32\"],\"memory\":[\"7168\"],\"type\":[\"id\"],\"version\":[\"1.3\"],\"parallelism\":[\"1\"]}}"
    } ],
    "disableableCredentialTypes" : [ ],
    "requiredActions" : [ ],
    "realmRoles" : [ "default-roles-user-realm" ],
    "clientRoles" : {
      "manav" : [ "customer" ]
    },
    "notBefore" : 0,
    "groups" : [ "/Dummy-Users" ]
  }, {
    "id" : "72945801-1d73-4104-b332-24944e53c9b6",
    "username" : "richard_b.__schwartz",
    "emailVerified" : true,
    "createdTimestamp" : 1740771097625,
    "enabled" : true,
    "totp" : false,
    "credentials" : [ {
      "id" : "ce23ef35-9a5f-42d7-8f75-85acbcc64d9f",
      "type" : "password",
      "createdDate" : 1740771097647,
      "secretData" : "{\"value\":\"4O27HqAqiE4BL9h0pkckb8kGf5S1fDJlJB+5iWMZ/2o=\",\"salt\":\"x8aPeHeqtI1ZjCnUN0zZoQ==\",\"additionalParameters\":{}}",
      "credentialData" : "{\"hashIterations\":5,\"algorithm\":\"argon2\",\"additionalParameters\":{\"hashLength\":[\"32\"],\"memory\":[\"7168\"],\"type\":[\"id\"],\"version\":[\"1.3\"],\"parallelism\":[\"1\"]}}"
    } ],
    "disableableCredentialTypes" : [ ],
    "requiredActions" : [ ],
    "realmRoles" : [ "default-roles-user-realm" ],
    "clientRoles" : {
      "manav" : [ "customer" ]
    },
    "notBefore" : 0,
    "groups" : [ "/Dummy-Users" ]
  }, {
    "id" : "095d8219-f81c-4f9c-8bed-0eb142b874a2",
    "username" : "richard_d.",
    "emailVerified" : true,
    "createdTimestamp" : 1740767442009,
    "enabled" : true,
    "totp" : false,
    "credentials" : [ {
      "id" : "7628071c-f50e-4da3-8073-299d73ada237",
      "type" : "password",
      "createdDate" : 1740767442026,
      "secretData" : "{\"value\":\"u0gnXR5uiAspctk2Oi89uvyOj5rn4cUVtQkQfGuJIco=\",\"salt\":\"uxTLW3RZ3unI6dQLeXJfKg==\",\"additionalParameters\":{}}",
      "credentialData" : "{\"hashIterations\":5,\"algorithm\":\"argon2\",\"additionalParameters\":{\"hashLength\":[\"32\"],\"memory\":[\"7168\"],\"type\":[\"id\"],\"version\":[\"1.3\"],\"parallelism\":[\"1\"]}}"
    } ],
    "disableableCredentialTypes" : [ ],
    "requiredActions" : [ ],
    "realmRoles" : [ "default-roles-user-realm" ],
    "clientRoles" : {
      "manav" : [ "customer" ]
    },
    "notBefore" : 0,
    "groups" : [ "/Dummy-Users" ]
  }, {
    "id" : "92113d75-75f1-446a-b53e-59725047948e",
    "username" : "richard_devlin",
    "emailVerified" : true,
    "createdTimestamp" : 1740768624610,
    "enabled" : true,
    "totp" : false,
    "credentials" : [ {
      "id" : "cbe81fbe-02a1-4ef8-9706-adbf1d614559",
      "type" : "password",
      "createdDate" : 1740768624625,
      "secretData" : "{\"value\":\"1QRMR4ckGssa1J7bMx3MlfU48ERTX4AjQef9qtREqzc=\",\"salt\":\"d81aLvDVVbptOUv4WSoVtA==\",\"additionalParameters\":{}}",
      "credentialData" : "{\"hashIterations\":5,\"algorithm\":\"argon2\",\"additionalParameters\":{\"hashLength\":[\"32\"],\"memory\":[\"7168\"],\"type\":[\"id\"],\"version\":[\"1.3\"],\"parallelism\":[\"1\"]}}"
    } ],
    "disableableCredentialTypes" : [ ],
    "requiredActions" : [ ],
    "realmRoles" : [ "default-roles-user-realm" ],
    "clientRoles" : {
      "manav" : [ "customer" ]
    },
    "notBefore" : 0,
    "groups" : [ "/Dummy-Users" ]
  }, {
    "id" : "71dc69df-1070-4fb5-be26-7f5b954d34fb",
    "username" : "richard_fargo",
    "emailVerified" : true,
    "createdTimestamp" : 1740769235859,
    "enabled" : true,
    "totp" : false,
    "credentials" : [ {
      "id" : "08bcf117-eb91-4cd2-8dce-2a84cb07a57f",
      "type" : "password",
      "createdDate" : 1740769235874,
      "secretData" : "{\"value\":\"wICtlzFhkLLprbj7Ios72Exi+XD/VuFXGA3iHCfyxOg=\",\"salt\":\"VakqI9ib8yxgrN6EryCV8w==\",\"additionalParameters\":{}}",
      "credentialData" : "{\"hashIterations\":5,\"algorithm\":\"argon2\",\"additionalParameters\":{\"hashLength\":[\"32\"],\"memory\":[\"7168\"],\"type\":[\"id\"],\"version\":[\"1.3\"],\"parallelism\":[\"1\"]}}"
    } ],
    "disableableCredentialTypes" : [ ],
    "requiredActions" : [ ],
    "realmRoles" : [ "default-roles-user-realm" ],
    "clientRoles" : {
      "manav" : [ "customer" ]
    },
    "notBefore" : 0,
    "groups" : [ "/Dummy-Users" ]
  }, {
    "id" : "572f0f88-54e4-451a-a6f5-8af2ee549c3d",
    "username" : "richard_franceli_tumioto",
    "emailVerified" : true,
    "createdTimestamp" : 1740769563436,
    "enabled" : true,
    "totp" : false,
    "credentials" : [ {
      "id" : "e7b98f76-d672-4c54-b89c-bacf5c570ea1",
      "type" : "password",
      "createdDate" : 1740769563451,
      "secretData" : "{\"value\":\"zqgCxPrnP2ls9aikYdW8+IBn+HjFrCwOzjqpIP0zIe4=\",\"salt\":\"VcigMrjcO6p0N4oge8a0kg==\",\"additionalParameters\":{}}",
      "credentialData" : "{\"hashIterations\":5,\"algorithm\":\"argon2\",\"additionalParameters\":{\"hashLength\":[\"32\"],\"memory\":[\"7168\"],\"type\":[\"id\"],\"version\":[\"1.3\"],\"parallelism\":[\"1\"]}}"
    } ],
    "disableableCredentialTypes" : [ ],
    "requiredActions" : [ ],
    "realmRoles" : [ "default-roles-user-realm" ],
    "clientRoles" : {
      "manav" : [ "customer" ]
    },
    "notBefore" : 0,
    "groups" : [ "/Dummy-Users" ]
  }, {
    "id" : "c04bb2eb-4d9f-446e-a81d-95652ddf9afd",
    "username" : "richard_frey",
    "emailVerified" : true,
    "createdTimestamp" : 1740768095109,
    "enabled" : true,
    "totp" : false,
    "credentials" : [ {
      "id" : "da59f303-f254-4712-8c35-1bb62657e3c9",
      "type" : "password",
      "createdDate" : 1740768095124,
      "secretData" : "{\"value\":\"Q72A14nnkPG6Skha7r/Zn17kT3dWHCTxtwXt7i09sFw=\",\"salt\":\"QB9USGq1RUxuIeYo5becQw==\",\"additionalParameters\":{}}",
      "credentialData" : "{\"hashIterations\":5,\"algorithm\":\"argon2\",\"additionalParameters\":{\"hashLength\":[\"32\"],\"memory\":[\"7168\"],\"type\":[\"id\"],\"version\":[\"1.3\"],\"parallelism\":[\"1\"]}}"
    } ],
    "disableableCredentialTypes" : [ ],
    "requiredActions" : [ ],
    "realmRoles" : [ "default-roles-user-realm" ],
    "clientRoles" : {
      "manav" : [ "customer" ]
    },
    "notBefore" : 0,
    "groups" : [ "/Dummy-Users" ]
  }, {
    "id" : "abd4b386-b27e-40f2-a39a-1f9b498ee020",
    "username" : "richard_holdsworth",
    "emailVerified" : true,
    "createdTimestamp" : 1740770120636,
    "enabled" : true,
    "totp" : false,
    "credentials" : [ {
      "id" : "3616e08b-d270-49fc-9383-6c567d31a0d7",
      "type" : "password",
      "createdDate" : 1740770120651,
      "secretData" : "{\"value\":\"f947/cO65ITce8VpEglyaccmDdLSKjr6nmUNJ7Q7u4Y=\",\"salt\":\"SUFzyIc+TQZPHutUGHaasw==\",\"additionalParameters\":{}}",
      "credentialData" : "{\"hashIterations\":5,\"algorithm\":\"argon2\",\"additionalParameters\":{\"hashLength\":[\"32\"],\"memory\":[\"7168\"],\"type\":[\"id\"],\"version\":[\"1.3\"],\"parallelism\":[\"1\"]}}"
    } ],
    "disableableCredentialTypes" : [ ],
    "requiredActions" : [ ],
    "realmRoles" : [ "default-roles-user-realm" ],
    "clientRoles" : {
      "manav" : [ "customer" ]
    },
    "notBefore" : 0,
    "groups" : [ "/Dummy-Users" ]
  }, {
    "id" : "ee053930-8950-42f4-bf4a-ea381e776139",
    "username" : "richard_howell",
    "emailVerified" : true,
    "createdTimestamp" : 1740772314546,
    "enabled" : true,
    "totp" : false,
    "credentials" : [ {
      "id" : "380acead-34ba-4a41-9dba-876c4103314c",
      "type" : "password",
      "createdDate" : 1740772314564,
      "secretData" : "{\"value\":\"P0WyZJpU9VwgVZ3eeWYVzHoj+trNqpg6WhU9dw4dTLw=\",\"salt\":\"s98POZp0qoveCOaVbWItlQ==\",\"additionalParameters\":{}}",
      "credentialData" : "{\"hashIterations\":5,\"algorithm\":\"argon2\",\"additionalParameters\":{\"hashLength\":[\"32\"],\"memory\":[\"7168\"],\"type\":[\"id\"],\"version\":[\"1.3\"],\"parallelism\":[\"1\"]}}"
    } ],
    "disableableCredentialTypes" : [ ],
    "requiredActions" : [ ],
    "realmRoles" : [ "default-roles-user-realm" ],
    "clientRoles" : {
      "manav" : [ "customer" ]
    },
    "notBefore" : 0,
    "groups" : [ "/Dummy-Users" ]
  }, {
    "id" : "3f113319-b7e4-4ab5-be17-ff3e0f8dd527",
    "username" : "richard_k.",
    "emailVerified" : true,
    "createdTimestamp" : 1740768682670,
    "enabled" : true,
    "totp" : false,
    "credentials" : [ {
      "id" : "b90f9681-6e0b-48f5-9f4b-53dd4eac0a40",
      "type" : "password",
      "createdDate" : 1740768682685,
      "secretData" : "{\"value\":\"dNEDStfvIlZo8fdKtlBf1WXUa1bNV0wnZjt/9MARc0w=\",\"salt\":\"euEpNKy/gO87X85p6QV5yQ==\",\"additionalParameters\":{}}",
      "credentialData" : "{\"hashIterations\":5,\"algorithm\":\"argon2\",\"additionalParameters\":{\"hashLength\":[\"32\"],\"memory\":[\"7168\"],\"type\":[\"id\"],\"version\":[\"1.3\"],\"parallelism\":[\"1\"]}}"
    } ],
    "disableableCredentialTypes" : [ ],
    "requiredActions" : [ ],
    "realmRoles" : [ "default-roles-user-realm" ],
    "clientRoles" : {
      "manav" : [ "customer" ]
    },
    "notBefore" : 0,
    "groups" : [ "/Dummy-Users" ]
  }, {
    "id" : "0b6f40e4-3e1e-4e01-9c8b-90d59311ce27",
    "username" : "richard_kline",
    "emailVerified" : true,
    "createdTimestamp" : 1740771639317,
    "enabled" : true,
    "totp" : false,
    "credentials" : [ {
      "id" : "c274f742-8e46-4148-aa52-de4a88246d6a",
      "type" : "password",
      "createdDate" : 1740771639332,
      "secretData" : "{\"value\":\"tYcT0h+risSc1ZwzgRf7Nmj9Vb8bEG9zMjMtjee7Q04=\",\"salt\":\"2uUHVLcmAz+zGmyz0IFA1g==\",\"additionalParameters\":{}}",
      "credentialData" : "{\"hashIterations\":5,\"algorithm\":\"argon2\",\"additionalParameters\":{\"hashLength\":[\"32\"],\"memory\":[\"7168\"],\"type\":[\"id\"],\"version\":[\"1.3\"],\"parallelism\":[\"1\"]}}"
    } ],
    "disableableCredentialTypes" : [ ],
    "requiredActions" : [ ],
    "realmRoles" : [ "default-roles-user-realm" ],
    "clientRoles" : {
      "manav" : [ "customer" ]
    },
    "notBefore" : 0,
    "groups" : [ "/Dummy-Users" ]
  }, {
    "id" : "bd43ea4a-e9ff-4bf7-a9a3-df215ba72398",
    "username" : "richard_l._yauman",
    "emailVerified" : true,
    "createdTimestamp" : 1740772391874,
    "enabled" : true,
    "totp" : false,
    "credentials" : [ {
      "id" : "b0c26133-e89c-4585-84c6-9583489f2696",
      "type" : "password",
      "createdDate" : 1740772391894,
      "secretData" : "{\"value\":\"pcj2E1vaKKX2el7FOhfFk02xr80M7SgvSgKAI47Kfeg=\",\"salt\":\"ixZ+BswOvdInrb0b0Elpog==\",\"additionalParameters\":{}}",
      "credentialData" : "{\"hashIterations\":5,\"algorithm\":\"argon2\",\"additionalParameters\":{\"hashLength\":[\"32\"],\"memory\":[\"7168\"],\"type\":[\"id\"],\"version\":[\"1.3\"],\"parallelism\":[\"1\"]}}"
    } ],
    "disableableCredentialTypes" : [ ],
    "requiredActions" : [ ],
    "realmRoles" : [ "default-roles-user-realm" ],
    "clientRoles" : {
      "manav" : [ "customer" ]
    },
    "notBefore" : 0,
    "groups" : [ "/Dummy-Users" ]
  }, {
    "id" : "ed3b141f-011d-4835-9650-d4f4019a23a0",
    "username" : "richard_lynch",
    "emailVerified" : true,
    "createdTimestamp" : 1740772087625,
    "enabled" : true,
    "totp" : false,
    "credentials" : [ {
      "id" : "d6b1d2f7-a787-497d-889b-4a03091a6d93",
      "type" : "password",
      "createdDate" : 1740772087641,
      "secretData" : "{\"value\":\"pV3Moh8uoRybQhO9xOAP0fE9TSBipcWKNOI4ytICjcw=\",\"salt\":\"bjAkiIL3SKfWYdjVfyyffQ==\",\"additionalParameters\":{}}",
      "credentialData" : "{\"hashIterations\":5,\"algorithm\":\"argon2\",\"additionalParameters\":{\"hashLength\":[\"32\"],\"memory\":[\"7168\"],\"type\":[\"id\"],\"version\":[\"1.3\"],\"parallelism\":[\"1\"]}}"
    } ],
    "disableableCredentialTypes" : [ ],
    "requiredActions" : [ ],
    "realmRoles" : [ "default-roles-user-realm" ],
    "clientRoles" : {
      "manav" : [ "customer" ]
    },
    "notBefore" : 0,
    "groups" : [ "/Dummy-Users" ]
  }, {
    "id" : "cdf636f6-7e45-41e1-b7eb-c39f07c474be",
    "username" : "richard_m.",
    "emailVerified" : true,
    "createdTimestamp" : 1740771216035,
    "enabled" : true,
    "totp" : false,
    "credentials" : [ {
      "id" : "850d2f7c-98f3-4af5-8b42-2ad229c80586",
      "type" : "password",
      "createdDate" : 1740771216051,
      "secretData" : "{\"value\":\"535RIGlvXujbwQmR+i0qu1V4S0sMkK31Kt9pb8jIZvU=\",\"salt\":\"XCC/uEtA+3uedavtc88DIA==\",\"additionalParameters\":{}}",
      "credentialData" : "{\"hashIterations\":5,\"algorithm\":\"argon2\",\"additionalParameters\":{\"hashLength\":[\"32\"],\"memory\":[\"7168\"],\"type\":[\"id\"],\"version\":[\"1.3\"],\"parallelism\":[\"1\"]}}"
    } ],
    "disableableCredentialTypes" : [ ],
    "requiredActions" : [ ],
    "realmRoles" : [ "default-roles-user-realm" ],
    "clientRoles" : {
      "manav" : [ "customer" ]
    },
    "notBefore" : 0,
    "groups" : [ "/Dummy-Users" ]
  } ]
}